hermes/__init__.py
hermes/__main__.py
hermes/common.py
hermes/setup.py
hermes/templates.py
hermes/version.py
hermes/bot/__init__.py
hermes/bot/fpower.py
hermes/bot/handlers.py
hermes/bot/linguist.py
hermes/bot/logger.py
hermes/task/__init__.py
hermes/task/linguist.py
hermes/task/logger.py
botHermes-2.2.0.post2.dist-info/LICENSE
botHermes-2.2.0.post2.dist-info/METADATA
botHermes-2.2.0.post2.dist-info/WHEEL
botHermes-2.2.0.post2.dist-info/entry_points.txt
botHermes-2.2.0.post2.dist-info/top_level.txt
botHermes-2.2.0.post2.dist-info/RECORD
