Metadata-Version: 2.1
Name: botHermes
Version: 2.2.0.post2
Summary: Telegram bot for messages, task notifications & system management
Author: Francesco Barone
License: Creative Commons Attribution-NonCommercial-NoDerivatives 4.0
Project-URL: Homepage, https://github.com/baronefr/hermes
Project-URL: Issues, https://github.com/baronefr/hermes/issues
Project-URL: Repository, https://github.com/baronefr/hermes
Project-URL: Documentation, https://bothermes.readthedocs.io
Classifier: Programming Language :: Python :: 3
Classifier: Operating System :: POSIX :: Linux
Requires-Python: >=3.8
License-File: LICENSE
Requires-Dist: pyTelegramBotAPI
Requires-Dist: termcolor
